{
  "pluginId": "default",
  "version": "current",
  "label": "Next",
  "banner": null,
  "badge": false,
  "className": "docs-version-current",
  "isLast": true,
  "docsSidebars": {
    "tutorialSidebar": [
      {
        "type": "link",
        "label": "Writing and Publications",
        "href": "/docs/list-of-works",
        "docId": "list-of-works"
      },
      {
        "type": "category",
        "label": "Writing Samples",
        "collapsible": true,
        "collapsed": true,
        "items": [
          {
            "type": "link",
            "label": "Defining The Word 'Wanting'",
            "href": "/docs/Writing Samples/defining-the-word-wanting",
            "docId": "Writing Samples/defining-the-word-wanting"
          }
        ]
      }
    ]
  },
  "docs": {
    "list-of-works": {
      "id": "list-of-works",
      "title": "Writing and Publications",
      "description": "Writing Samples",
      "sidebar": "tutorialSidebar"
    },
    "Writing Samples/defining-the-word-wanting": {
      "id": "Writing Samples/defining-the-word-wanting",
      "title": "Defining The Word Wanting",
      "description": "written June 2021, published in Stem to Sternum January 2022",
      "sidebar": "tutorialSidebar"
    }
  }
}